nacal/__init__.py
nacal/nacal.py
nacal-0.2.2.dist-info/LICENSE
nacal-0.2.2.dist-info/METADATA
nacal-0.2.2.dist-info/WHEEL
nacal-0.2.2.dist-info/top_level.txt
nacal-0.2.2.dist-info/RECORD
