Metadata-Version: 2.1
Name: nacal
Version: 0.2.2
Summary: Notacion Asociativa para un curso de Algebra Lineal (NAcAL)
Home-page: https://github.com/mbujosab/nacallib
Author: Marcos Bujosa
Author-email: mbujosab@ucm.es
License: GPLv3
Keywords: nacal
Classifier: Programming Language :: Python :: 3
Classifier: License :: OSI Approved :: GNU General Public License v3 (GPLv3)
Classifier: Operating System :: OS Independent
Classifier: Intended Audience :: Education
Classifier: Framework :: Jupyter
Classifier: Environment :: Console
Classifier: Natural Language :: Spanish
Classifier: Topic :: Scientific/Engineering :: Mathematics
Classifier: Development Status :: 3 - Alpha
Requires-Python: >=3.6
License-File: LICENSE
Requires-Dist: sympy (>=1.1.0)
